LICENSE.txt
README.md
setup.cfg
setup.py
MinioProgress/Progress.py
MinioProgress/__init__.py
MinioProgress.egg-info/PKG-INFO
MinioProgress.egg-info/SOURCES.txt
MinioProgress.egg-info/dependency_links.txt
MinioProgress.egg-info/top_level.txt