Metadata-Version: 2.2
Name: MinioProgress
Version: 0.1.1
Summary: Progress Bar for Minio
Home-page: https://github.com/limangit/MinioProgress
Download-URL: https://github.com/LimanGit/MinioProgress/archive/refs/tags/v0.1.1.zip
Author: LimanOP
Author-email: liman@realiman.lol
License: MIT
Keywords: Minio,S3,Python,Progress
Classifier: Development Status :: 3 - Alpha
Classifier: Intended Audience :: Developers
Classifier: Topic :: Software Development :: Build Tools
Classifier: License :: OSI Approved :: MIT License
Classifier: Programming Language :: Python :: 3
Classifier: Programming Language :: Python :: 3.4
Classifier: Programming Language :: Python :: 3.5
Classifier: Programming Language :: Python :: 3.6
License-File: LICENSE.txt
Dynamic: author
Dynamic: author-email
Dynamic: classifier
Dynamic: download-url
Dynamic: home-page
Dynamic: keywords
Dynamic: license
Dynamic: summary
